LICENSE
README.rst
setup.py
sfft/AutoCrowdedPrep.py
sfft/AutoSparsePrep.py
sfft/BSplineSFFT.py
sfft/CustomizedPacket.py
sfft/EasyCrowdedPacket.py
sfft/EasySparsePacket.py
sfft/MultiEasyCrowdedPacket.py
sfft/MultiEasySparsePacket.py
sfft/PureCupyCustomizedPacket.py
sfft/SpaceSFFTCupyFlow.py
sfft/__init__.py
sfft/sfftcore/SFFTConfigure.py
sfft/sfftcore/SFFTSubtract.py
sfft/sfftcore/__init__.py
sfft/utils/CombineHeader.py
sfft/utils/ConvKernelConvertion.py
sfft/utils/CupyWCSTransform.py
sfft/utils/DeCorrelationCalculator.py
sfft/utils/DeCorrelationCalculatorDep.py
sfft/utils/HoughDetection.py
sfft/utils/HoughMorphClassifier.py
sfft/utils/ImageZoomRotate.py
sfft/utils/NeighboringPixelCovariance.py
sfft/utils/PatternRotationCalculator.py
sfft/utils/PureCupyDeCorrelationCalculator.py
sfft/utils/PureCupyFFTKits.py
sfft/utils/ReadWCS.py
sfft/utils/ResampKits.py
sfft/utils/SExSkySubtract.py
sfft/utils/SFFTSolutionReader.py
sfft/utils/SkyLevelEstimator.py
sfft/utils/StampGenerator.py
sfft/utils/SymmetricMatch.py
sfft/utils/WeightedQuantile.py
sfft/utils/__init__.py
sfft/utils/meta/MultiProc.py
sfft/utils/meta/TimeoutKit.py
sfft/utils/meta/__init__.py
sfft/utils/pyAstroMatic/AMConfigMaker.py
sfft/utils/pyAstroMatic/PYSEx.py
sfft/utils/pyAstroMatic/PYSWarp.py
sfft/utils/pyAstroMatic/__init__.py
sfft_romansnpit.egg-info/PKG-INFO
sfft_romansnpit.egg-info/SOURCES.txt
sfft_romansnpit.egg-info/dependency_links.txt
sfft_romansnpit.egg-info/not-zip-safe
sfft_romansnpit.egg-info/requires.txt
sfft_romansnpit.egg-info/top_level.txt