Metadata-Version: 2.4
Name: sfft-romansnpit
Version: 1.6.4.dev12
Summary: Image Subtraction in Fourier Space
Download-URL: https://github.com/thomasvrussell/sfft
Author: Lei Hu
Author-email: leihu@andrew.cmu.edu
Maintainer: Lei Hu
Maintainer-email: leihu@andrew.cmu.edu
License: MIT License
Classifier: Development Status :: 4 - Beta
Classifier: Environment :: Console
Classifier: Intended Audience :: Science/Research
Classifier: Natural Language :: English
Classifier: Programming Language :: Python :: 3.10
Classifier: Programming Language :: Python :: 3 :: Only
Classifier: Topic :: Scientific/Engineering :: Astronomy
License-File: LICENSE
Requires-Dist: scipy>=1.5.2
Requires-Dist: astropy>=3.2.3
Requires-Dist: scikit-image>=0.25.2
Requires-Dist: fastremap>=1.7.0
Requires-Dist: sep>=1.0.3
Requires-Dist: numba>=0.53.1
Requires-Dist: llvmlite>=0.36.0
Requires-Dist: pyfftw>=0.12.0
Dynamic: author
Dynamic: author-email
Dynamic: classifier
Dynamic: description
Dynamic: description-content-type
Dynamic: download-url
Dynamic: license
Dynamic: license-file
Dynamic: maintainer
Dynamic: maintainer-email
Dynamic: requires-dist
Dynamic: summary
